{
  "Abass": 6,
  "Abdou": 8,
  "Abdoul": 21,
  "Abdoul Aziz": 10,
  "Abdoulaye": 51,
  "Abibata": 6,
  "Aboubacar": 21,
  "Adama": 89,
  "Adja": 6,
  "Adjara": 8,
  "Aicha": 14,
  "Aida": 6,
  "Alassane": 41,
  "Alexis": 6,
  "Ali": 31,
  "Alice": 6,
  "Alidou": 13,
  "Alima": 11,
  "Amado": 6,
  "Amadou": 18,
  "Amed": 8,
  "Ami": 9,
  "Amidou": 11,
  "Aminata": 21,
  "Arouna": 16,
  "Assami": 9,
  "Assane": 6,
  "Assetou": 9,
  "Augustin": 9,
  "Awa": 21,
  "Aziz": 24,
  "Aïcha": 8,
  "Bakary": 6,
  "Bara": 6,
  "Bassirou": 11,
  "Belem": 7,
  "Benjamin": 7,
  "Bernard": 8,
  "Biba": 10,
  "Bibata": 7,
  "Bintou": 10,
  "Blandine": 7,
  "Bouba": 11,
  "Boubakar": 7,
  "Boukare": 6,
  "Boukari": 6,
  "Boukary": 10,
  "Boureima": 47,
  "Catherine": 8,
  "Cheick": 6,
  "Christian": 6,
  "Compaore": 11,
  "Daniel": 11,
  "Daouda": 39,
  "David": 17,
  "Didier": 7,
  "Djeneba": 14,
  "Dramane": 18,
  "Drissa": 17,
  "Edmond": 6,
  "Elie": 6,
  "Emmanuel": 12,
  "Eric": 7,
  "Fabrice": 6,
  "Fanta": 7,
  "Fatim": 11,
  "Fatimata": 22,
  "Fatou": 6,
  "Fatoumata": 14,
  "François": 6,
  "Hamado": 17,
  "Hamadou": 8,
  "Hamed": 7,
  "Hamidou": 32,
  "Harouna": 29,
  "Hermann": 6,
  "Ibrahim": 44,
  "Ibrahima": 8,
  "Idrissa": 36,
  "Inoussa": 35,
  "Isabelle": 6,
  "Ismael": 6,
  "Issa": 53,
  "Issaka": 33,
  "Issiaka": 9,
  "Issouf": 44,
  "Issoufou": 6,
  "Jacques": 6,
  "Jean": 7,
  "Joseph": 6,
  "Kabore": 29,
  "Kader": 11,
  "Kadi": 13,
  "Karim": 45,
  "Kassoum": 12,
  "Lamine": 7,
  "Lassina": 11,
  "Laurent": 7,
  "Madi": 37,
  "Mahamadi": 19,
  "Mahamoudou": 14,
  "Mamadou": 16,
  "Mamoudou": 9,
  "Mariam": 49,
  "Marie": 8,
  "Mathias": 6,
  "Mathieu": 6,
  "Michel": 8,
  "Mohamed": 37,
  "Moumouni": 25,
  "Mouni": 6,
  "Moussa": 72,
  "Moustapha": 9,
  "Nafissatou": 6,
  "Nana": 9,
  "Nicolas": 7,
  "Nikiema": 8,
  "Noufou": 9,
  "Omar": 24,
  "Ouattara": 8,
  "Ouedraogo": 67,
  "Oumar": 18,
  "Oumarou": 29,
  "Ousmane": 40,
  "Ousseni": 16,
  "Pascal": 10,
  "Paul": 13,
  "Rabo": 7,
  "Rachid": 6,
  "Rasmane": 15,
  "Rasmané": 6,
  "Rasmata": 10,
  "Raso": 6,
  "Robert": 10,
  "Roger": 8,
  "Safi": 8,
  "Safiatou": 8,
  "Saidou": 23,
  "Salam": 10,
  "Salamata": 10,
  "Sali": 13,
  "Salif": 32,
  "Salifou": 7,
  "Salimata": 11,
  "Salomon": 6,
  "Samira": 6,
  "Sanata": 9,
  "Sanfo": 6,
  "Sanou": 11,
  "Savadogo": 8,
  "Sawadogo": 30,
  "Sayouba": 32,
  "Seni": 11,
  "Seydou": 23,
  "Siaka": 9,
  "Sidiki": 6,
  "Sita": 9,
  "Soulemane": 9,
  "Souley": 6,
  "Souleymane": 56,
  "Soumaila": 18,
  "Soumaïla": 10,
  "Sylvain": 9,
  "Sylvie": 6,
  "Tassere": 9,
  "Traore": 11,
  "Traoré": 6,
  "Yacou": 7,
  "Yacouba": 43,
  "Yassia": 10,
  "Yaya": 14,
  "Zakaria": 30,
  "Zalissa": 9,
  "Zongo": 12
}